Processador Multiciclo/made_parts/div.sv
//`timescale 1ns/1ps
module div(
  input wire clk,  
  input wire rst,  
  input wire start,
  input wire [31:0] a,
  input wire [31:0] b,
  output reg busy,
  output reg done,
  output reg dbz,
  output reg [31:0] val,
  output reg [31:0] rem
);

  reg [31:0] quo;
  reg [32:0] acc;
  reg [31:0] A;
  reg [31:0] B;
  reg [6:0] i;
  reg neg;

initial busy = 1'b0; // -------- mais 

  always @(posedge clk) begin
    if (start && !busy && !done) begin
      i = 0;
      if (b == 0) begin // divisão por zero
        busy = 0;
        done = 1;
        dbz = 1;
      end else begin // começo
        neg = 1'b0;
        busy = 1;
        dbz = 0;
        if (b[31] == 1) begin // b negativo
          neg = ~neg; B = ~b+1; 
        end
        else begin 
          B = b; 
        end
        if (a[31] == 1) begin // a negativo
          neg = ~neg; A = ~a+1; 
        end
        else begin 
          A = a; 
        end
        {acc, quo} ={{32{1'b0}}, A, 1'b0};
      end
    end else if (busy) begin // procedimento
      if (i == 32) begin  // fim
        busy = 0;
        done = 1;
        if (neg) begin 
          val = ~quo+1; 
        end else begin 
          val = quo; 
        end
        rem = acc[31:1];
      end else begin  // operação
        i = i + 1;
        if (acc >= {1'b0, B}) begin
          acc = acc - B;
          {acc, quo} = {acc[31:0], quo, 1'b1};
        end else begin
          {acc, quo} = {acc, quo} << 1;
        end
      end
    end else if (done) begin //fim
      busy = 0;
      done = 1;
      if (neg) begin 
        val = ~quo+1; 
      end else begin 
        val = quo; 
      end
      rem = acc[31:1];
    end
    if (rst) begin
      busy = 0;
      done = 0;
      dbz = 0;
      val = 0;
      rem = 0;
    end
  end
endmodule

Processador Multiciclo/made_parts/div_tb.sv
`timescale 1ps/1ps

module div_tb(
    output reg busy,
    output reg done,
    output reg dbz,
    output reg [31:0] val,
    output reg [31:0] rem
);
  
    reg clk;  
    reg rst;  
    reg start;
    reg [31:0] a;
    reg [31:0] b;


  integer i,j;
  
  div dut(
    .clk(clk),
    .rst(rst),
    .start(start),
    .busy(busy),
    .done(done),
    .dbz(dbz),
    .a(a),
    .b(b),
    .val(val),
    .rem(rem)
  );


 initial begin 
   clk = 0; 
   forever begin
    #1 clk = ~clk;
 end end
  
  initial begin
    $dumpfile("dump.vcd");
    $dumpvars(0, div_tb);
    
    start = 1'b1;
    
	 for (i = 1000; i < 10000; i = i + 1000)
      begin
        #5 a <= i;
        for (j = 7; j > -5; j = j - 1)
        begin
            #5 b <= j;
          #200
          $display("i = %d, j = %d, val = %d, rem = %d",i,j,$signed(val),rem);
        end
      end
    // $display("quo: %d", $signed(val));
    
    #5 $finish;
    
  end
 
endmodule

dump.vcd
$date
	Wed Aug 09 23:42:43 2023
$end
$version
	ModelSim Version 2020.1
$end
$timescale
	1ps
$end

$scope module div_tb $end
$var reg 1 ! busy $end
$var reg 1 " done $end
$var reg 1 # dbz $end
$var reg 32 $ val [31:0] $end
$var reg 32 % rem [31:0] $end
$var reg 1 & clk $end
$var reg 1 ' rst $end
$var reg 1 ( start $end
$var reg 32 ) a [31:0] $end
$var reg 32 * b [31:0] $end
$var integer 32 + i $end
$var integer 32 , j $end

$scope module dut $end
$var wire 1 - clk $end
$var wire 1 . rst $end
$var wire 1 / start $end
$var reg 1 0 busy $end
$var reg 1 1 done $end
$var reg 1 2 dbz $end
$var wire 1 3 a [31] $end
$var wire 1 4 a [30] $end
$var wire 1 5 a [29] $end
$var wire 1 6 a [28] $end
$var wire 1 7 a [27] $end
$var wire 1 8 a [26] $end
$var wire 1 9 a [25] $end
$var wire 1 : a [24] $end
$var wire 1 ; a [23] $end
$var wire 1 < a [22] $end
$var wire 1 = a [21] $end
$var wire 1 > a [20] $end
$var wire 1 ? a [19] $end
$var wire 1 @ a [18] $end
$var wire 1 A a [17] $end
$var wire 1 B a [16] $end
$var wire 1 C a [15] $end
$var wire 1 D a [14] $end
$var wire 1 E a [13] $end
$var wire 1 F a [12] $end
$var wire 1 G a [11] $end
$var wire 1 H a [10] $end
$var wire 1 I a [9] $end
$var wire 1 J a [8] $end
$var wire 1 K a [7] $end
$var wire 1 L a [6] $end
$var wire 1 M a [5] $end
$var wire 1 N a [4] $end
$var wire 1 O a [3] $end
$var wire 1 P a [2] $end
$var wire 1 Q a [1] $end
$var wire 1 R a [0] $end
$var wire 1 S b [31] $end
$var wire 1 T b [30] $end
$var wire 1 U b [29] $end
$var wire 1 V b [28] $end
$var wire 1 W b [27] $end
$var wire 1 X b [26] $end
$var wire 1 Y b [25] $end
$var wire 1 Z b [24] $end
$var wire 1 [ b [23] $end
$var wire 1 \ b [22] $end
$var wire 1 ] b [21] $end
$var wire 1 ^ b [20] $end
$var wire 1 _ b [19] $end
$var wire 1 ` b [18] $end
$var wire 1 a b [17] $end
$var wire 1 b b [16] $end
$var wire 1 c b [15] $end
$var wire 1 d b [14] $end
$var wire 1 e b [13] $end
$var wire 1 f b [12] $end
$var wire 1 g b [11] $end
$var wire 1 h b [10] $end
$var wire 1 i b [9] $end
$var wire 1 j b [8] $end
$var wire 1 k b [7] $end
$var wire 1 l b [6] $end
$var wire 1 m b [5] $end
$var wire 1 n b [4] $end
$var wire 1 o b [3] $end
$var wire 1 p b [2] $end
$var wire 1 q b [1] $end
$var wire 1 r b [0] $end
$var reg 32 s val [31:0] $end
$var reg 32 t rem [31:0] $end
$var reg 32 u quo [31:0] $end
$var reg 33 v acc [32:0] $end
$var reg 32 w A [31:0] $end
$var reg 32 x B [31:0] $end
$var reg 7 y i [6:0] $end
$var reg 1 z neg $end
$upscope $end
$upscope $end
$enddefinitions $end
#0
$dumpvars
0!
x"
x#
bx $
bx %
0&
x'
1(
bx )
bx *
00
x1
x2
bx s
bx t
bx u
bx v
bx w
bx x
bx y
xz
b1111101000 +
bx ,
0-
x.
1/
xR
xQ
xP
xO
xN
xM
xL
xK
xJ
xI
xH
xG
xF
xE
xD
xC
xB
xA
x@
x?
x>
x=
x<
x;
x:
x9
x8
x7
x6
x5
x4
x3
xr
xq
xp
xo
xn
xm
xl
xk
xj
xi
xh
xg
xf
xe
xd
xc
xb
xa
x`
x_
x^
x]
x\
x[
xZ
xY
xX
xW
xV
xU
xT
xS
$end
#1
1&
1-
01
b0 y
0z
10
02
bx0 u
b0x v
0#
1!
0"
#2
0&
0-
#3
1&
1-
b1 y
bx00 u
b0xx v
#4
0&
0-
#5
b111 ,
1&
1-
b10 y
bx000 u
b0xxx v
b1111101000 )
0R
0Q
0P
1O
0N
1M
1L
1K
1J
1I
0H
0G
0F
0E
0D
0C
0B
0A
0@
0?
0>
0=
0<
0;
0:
09
08
07
06
05
04
03
#6
0&
0-
#7
1&
1-
b11 y
bx0000 u
b0xxxx v
#8
0&
0-
#9
1&
1-
b100 y
bx00000 u
b0xxxxx v
#10
0&
0-
b111 *
1r
1q
1p
0o
0n
0m
0l
0k
0j
0i
0h
0g
0f
0e
0d
0c
0b
0a
0`
0_
0^
0]
0\
0[
0Z
0Y
0X
0W
0V
0U
0T
0S
#11
1&
1-
b101 y
bx000000 u
b0xxxxxx v
#12
0&
0-
#13
1&
1-
b110 y
bx0000000 u
b0xxxxxxx v
#14
0&
0-
#15
1&
1-
b111 y
bx00000000 u
b0xxxxxxxx v
#16
0&
0-
#17
1&
1-
b1000 y
bx000000000 u
b0xxxxxxxxx v
#18
0&
0-
#19
1&
1-
b1001 y
bx0000000000 u
b0xxxxxxxxxx v
#20
0&
0-
#21
1&
1-
b1010 y
bx00000000000 u
b0xxxxxxxxxxx v
#22
0&
0-
#23
1&
1-
b1011 y
bx000000000000 u
b0xxxxxxxxxxxx v
#24
0&
0-
#25
1&
1-
b1100 y
bx0000000000000 u
b0xxxxxxxxxxxxx v
#26
0&
0-
#27
1&
1-
b1101 y
bx00000000000000 u
b0xxxxxxxxxxxxxx v
#28
0&
0-
#29
1&
1-
b1110 y
bx000000000000000 u
b0xxxxxxxxxxxxxxx v
#30
0&
0-
#31
1&
1-
b1111 y
bx0000000000000000 u
b0xxxxxxxxxxxxxxxx v
#32
0&
0-
#33
1&
1-
b10000 y
bx00000000000000000 u
b0xxxxxxxxxxxxxxxxx v
#34
0&
0-
#35
1&
1-
b10001 y
bx000000000000000000 u
b0xxxxxxxxxxxxxxxxxx v
#36
0&
0-
#37
1&
1-
b10010 y
bx0000000000000000000 u
b0xxxxxxxxxxxxxxxxxxx v
#38
0&
0-
#39
1&
1-
b10011 y
bx00000000000000000000 u
b0xxxxxxxxxxxxxxxxxxxx v
#40
0&
0-
#41
1&
1-
b10100 y
bx000000000000000000000 u
b0xxxxxxxxxxxxxxxxxxxxx v
#42
0&
0-
#43
1&
1-
b10101 y
bx0000000000000000000000 u
b0xxxxxxxxxxxxxxxxxxxxxx v
#44
0&
0-
#45
1&
1-
b10110 y
bx00000000000000000000000 u
b0xxxxxxxxxxxxxxxxxxxxxxx v
#46
0&
0-
#47
1&
1-
b10111 y
bx000000000000000000000000 u
b0xxxxxxxxxxxxxxxxxxxxxxxx v
#48
0&
0-
#49
1&
1-
b11000 y
bx0000000000000000000000000 u
b0xxxxxxxxxxxxxxxxxxxxxxxxx v
#50
0&
0-
#51
1&
1-
b11001 y
bx00000000000000000000000000 u
b0xxxxxxxxxxxxxxxxxxxxxxxxxx v
#52
0&
0-
#53
1&
1-
b11010 y
bx000000000000000000000000000 u
b0xxxxxxxxxxxxxxxxxxxxxxxxxxx v
#54
0&
0-
#55
1&
1-
b11011 y
bx0000000000000000000000000000 u
b0xxxxxxxxxxxxxxxxxxxxxxxxxxxx v
#56
0&
0-
#57
1&
1-
b11100 y
bx00000000000000000000000000000 u
b0xxxxxxxxxxxxxxxxxxxxxxxxxxxxx v
#58
0&
0-
#59
1&
1-
b11101 y
bx000000000000000000000000000000 u
b0xxxxxxxxxxxxxxxxxxxxxxxxxxxxxx v
#60
0&
0-
#61
1&
1-
b11110 y
bx0000000000000000000000000000000 u
b0xxxxxxxxxxxxxxxxxxxxxxxxxxxxxxx v
#62
0&
0-
#63
1&
1-
b11111 y
b0 u
b0xxxxxxxxxxxxxxxxxxxxxxxxxxxxxxxx v
#64
0&
0-
#65
1&
1-
b100000 y
bx0 v
#66
0&
0-
#67
1&
1-
00
11
b0 s
b0xxxxxxxxxxxxxxxxxxxxxxxxxxxxxxx t
b0xxxxxxxxxxxxxxxxxxxxxxxxxxxxxxx %
b0 $
1"
0!
#68
0&
0-
#69
1&
1-
01
b0 y
10
b111 x
b1111101000 w
b11111010000 u
b0 v
1!
0"
#70
0&
0-
#71
1&
1-
b1 y
b111110100000 u
#72
0&
0-
#73
1&
1-
b10 y
b1111101000000 u
#74
0&
0-
#75
1&
1-
b11 y
b11111010000000 u
#76
0&
0-
#77
1&
1-
b100 y
b111110100000000 u
#78
0&
0-
#79
1&
1-
b101 y
b1111101000000000 u
#80
0&
0-
#81
1&
1-
b110 y
b11111010000000000 u
#82
0&
0-
#83
1&
1-
b111 y
b111110100000000000 u
#84
0&
0-
#85
1&
1-
b1000 y
b1111101000000000000 u
#86
0&
0-
#87
1&
1-
b1001 y
b11111010000000000000 u
#88
0&
0-
#89
1&
1-
b1010 y
b111110100000000000000 u
#90
0&
0-
#91
1&
1-
b1011 y
b1111101000000000000000 u
#92
0&
0-
#93
1&
1-
b1100 y
b11111010000000000000000 u
#94
0&
0-
#95
1&
1-
b1101 y
b111110100000000000000000 u
#96
0&
0-
#97
1&
1-
b1110 y
b1111101000000000000000000 u
#98
0&
0-
#99
1&
1-
b1111 y
b11111010000000000000000000 u
#100
0&
0-
#101
1&
1-
b10000 y
b111110100000000000000000000 u
#102
0&
0-
#103
1&
1-
b10001 y
b1111101000000000000000000000 u
#104
0&
0-
#105
1&
1-
b10010 y
b11111010000000000000000000000 u
#106
0&
0-
#107
1&
1-
b10011 y
b111110100000000000000000000000 u
#108
0&
0-
#109
1&
1-
b10100 y
b1111101000000000000000000000000 u
#110
0&
0-
#111
1&
1-
b10101 y
b11111010000000000000000000000000 u
#112
0&
0-
#113
1&
1-
b10110 y
b11110100000000000000000000000000 u
b1 v
#114
0&
0-
#115
1&
1-
b10111 y
b11101000000000000000000000000000 u
b11 v
#116
0&
0-
#117
1&
1-
b11000 y
b11010000000000000000000000000000 u
b111 v
#118
0&
0-
#119
1&
1-
b11001 y
b0 v
b10100000000000000000000000000001 u
b1 v
#120
0&
0-
#121
1&
1-
b11010 y
b1000000000000000000000000000010 u
b11 v
#122
0&
0-
#123
1&
1-
b11011 y
b10000000000000000000000000000100 u
b110 v
#124
0&
0-
#125
1&
1-
b11100 y
b1000 u
b1101 v
#126
0&
0-
#127
1&
1-
b11101 y
b110 v
b10001 u
b1100 v
#128
0&
0-
#129
1&
1-
b11110 y
b101 v
b100011 u
b1010 v
#130
0&
0-
#131
1&
1-
b11111 y
b11 v
b1000111 u
b110 v
#132
0&
0-
#133
1&
1-
b100000 y
b10001110 u
b1100 v
#134
0&
0-
#135
1&
1-
00
11
b10001110 s
b110 t
b110 %
b10001110 $
1"
0!
#136
0&
0-
#137
1&
1-
01
b0 y
10
b11111010000 u
b0 v
1!
0"
#138
0&
0-
#139
1&
1-
b1 y
b111110100000 u
#140
0&
0-
#141
1&
1-
b10 y
b1111101000000 u
#142
0&
0-
#143
1&
1-
b11 y
b11111010000000 u
#144
0&
0-
#145
1&
1-
b100 y
b111110100000000 u
#146
0&
0-
#147
1&
1-
b101 y
b1111101000000000 u
#148
0&
0-
#149
1&
1-
b110 y
b11111010000000000 u
#150
0&
0-
#151
1&
1-
b111 y
b111110100000000000 u
#152
0&
0-
#153
1&
1-
b1000 y
b1111101000000000000 u
#154
0&
0-
#155
1&
1-
b1001 y
b11111010000000000000 u
#156
0&
0-
#157
1&
1-
b1010 y
b111110100000000000000 u
#158
0&
0-
#159
1&
1-
b1011 y
b1111101000000000000000 u
#160
0&
0-
#161
1&
1-
b1100 y
b11111010000000000000000 u
#162
0&
0-
#163
1&
1-
b1101 y
b111110100000000000000000 u
#164
0&
0-
#165
1&
1-
b1110 y
b1111101000000000000000000 u
#166
0&
0-
#167
1&
1-
b1111 y
b11111010000000000000000000 u
#168
0&
0-
#169
1&
1-
b10000 y
b111110100000000000000000000 u
#170
0&
0-
#171
1&
1-
b10001 y
b1111101000000000000000000000 u
#172
0&
0-
#173
1&
1-
b10010 y
b11111010000000000000000000000 u
#174
0&
0-
#175
1&
1-
b10011 y
b111110100000000000000000000000 u
#176
0&
0-
#177
1&
1-
b10100 y
b1111101000000000000000000000000 u
#178
0&
0-
#179
1&
1-
b10101 y
b11111010000000000000000000000000 u
#180
0&
0-
#181
1&
1-
b10110 y
b11110100000000000000000000000000 u
b1 v
#182
0&
0-
#183
1&
1-
b10111 y
b11101000000000000000000000000000 u
b11 v
#184
0&
0-
#185
1&
1-
b11000 y
b11010000000000000000000000000000 u
b111 v
#186
0&
0-
#187
1&
1-
b11001 y
b0 v
b10100000000000000000000000000001 u
b1 v
#188
0&
0-
#189
1&
1-
b11010 y
b1000000000000000000000000000010 u
b11 v
#190
0&
0-
#191
1&
1-
b11011 y
b10000000000000000000000000000100 u
b110 v
#192
0&
0-
#193
1&
1-
b11100 y
b1000 u
b1101 v
#194
0&
0-
#195
1&
1-
b11101 y
b110 v
b10001 u
b1100 v
#196
0&
0-
#197
1&
1-
b11110 y
b101 v
b100011 u
b1010 v
#198
0&
0-
#199
1&
1-
b11111 y
b11 v
b1000111 u
b110 v
#200
0&
0-
#201
1&
1-
b100000 y
b10001110 u
b1100 v
#202
0&
0-
#203
1&
1-
00
11
1"
0!
#204
0&
0-
#205
1&
1-
01
b0 y
10
b11111010000 u
b0 v
1!
0"
#206
0&
0-
#207
1&
1-
b1 y
b111110100000 u
#208
0&
0-
#209
1&
1-
b10 y
b1111101000000 u
#210
b110 ,
0&
0-
#211
1&
1-
b11 y
b11111010000000 u
#212
0&
0-
#213
1&
1-
b100 y
b111110100000000 u
#214
0&
0-
#215
1&
1-
b101 y
b1111101000000000 u
b110 *
0r
#216
0&
0-
#217
1&
1-
b110 y
b11111010000000000 u
#218
0&
0-
#219
1&
1-
b111 y
b111110100000000000 u
#220
0&
0-
#221
1&
1-
b1000 y
b1111101000000000000 u
#222
0&
0-
#223
1&
1-
b1001 y
b11111010000000000000 u
#224
0&
0-
#225
1&
1-
b1010 y
b111110100000000000000 u
#226
0&
0-
#227
1&
1-
b1011 y
b1111101000000000000000 u
#228
0&
0-
#229
1&
1-
b1100 y
b11111010000000000000000 u
#230
0&
0-
#231
1&
1-
b1101 y
b111110100000000000000000 u
#232
0&
0-
#233
1&
1-
b1110 y
b1111101000000000000000000 u
#234
0&
0-
#235
1&
1-
b1111 y
b11111010000000000000000000 u
#236
0&
0-
#237
1&
1-
b10000 y
b111110100000000000000000000 u
#238
0&
0-
#239
1&
1-
b10001 y
b1111101000000000000000000000 u
#240
0&
0-
#241
1&
1-
b10010 y
b11111010000000000000000000000 u
#242
0&
0-
#243
1&
1-
b10011 y
b111110100000000000000000000000 u
#244
0&
0-
#245
1&
1-
b10100 y
b1111101000000000000000000000000 u
#246
0&
0-
#247
1&
1-
b10101 y
b11111010000000000000000000000000 u
#248
0&
0-
#249
1&
1-
b10110 y
b11110100000000000000000000000000 u
b1 v
#250
0&
0-
#251
1&
1-
b10111 y
b11101000000000000000000000000000 u
b11 v
#252
0&
0-
#253
1&
1-
b11000 y
b11010000000000000000000000000000 u
b111 v
#254
0&
0-
#255
1&
1-
b11001 y
b0 v
b10100000000000000000000000000001 u
b1 v
#256
0&
0-
#257
1&
1-
b11010 y
b1000000000000000000000000000010 u
b11 v
#258
0&
0-
#259
1&
1-
b11011 y
b10000000000000000000000000000100 u
b110 v
#260
0&
0-
#261
1&
1-
b11100 y
b1000 u
b1101 v
#262
0&
0-
#263
1&
1-
b11101 y
b110 v
b10001 u
b1100 v
#264
0&
0-
#265
1&
1-
b11110 y
b101 v
b100011 u
b1010 v
#266
0&
0-
#267
1&
1-
b11111 y
b11 v
b1000111 u
b110 v
#268
0&
0-
#269
1&
1-
b100000 y
b10001110 u
b1100 v
#270
0&
0-
#271
1&
1-
00
11
1"
0!
#272
0&
0-
#273
1&
1-
01
b0 y
10
b110 x
b11111010000 u
b0 v
1!
0"
#274
0&
0-
#275
1&
1-
b1 y
b111110100000 u
#276
0&
0-
#277
1&
1-
b10 y
b1111101000000 u
#278
0&
0-
#279
1&
1-
b11 y
b11111010000000 u
#280
0&
0-
#281
1&
1-
b100 y
b111110100000000 u
#282
0&
0-
#283
1&
1-
b101 y
b1111101000000000 u
#284
0&
0-
#285
1&
1-
b110 y
b11111010000000000 u
#286
0&
0-
#287
1&
1-
b111 y
b111110100000000000 u
#288
0&
0-
#289
1&
1-
b1000 y
b1111101000000000000 u
#290
0&
0-
#291
1&
1-
b1001 y
b11111010000000000000 u
#292
0&
0-
#293
1&
1-
b1010 y
b111110100000000000000 u
#294
0&
0-
#295
1&
1-
b1011 y
b1111101000000000000000 u
#296
0&
0-
#297
1&
1-
b1100 y
b11111010000000000000000 u
#298
0&
0-
#299
1&
1-
b1101 y
b111110100000000000000000 u
#300
0&
0-
#301
1&
1-
b1110 y
b1111101000000000000000000 u
#302
0&
0-
#303
1&
1-
b1111 y
b11111010000000000000000000 u
#304
0&
0-
#305
1&
1-
b10000 y
b111110100000000000000000000 u
#306
0&
0-
#307
1&
1-
b10001 y
b1111101000000000000000000000 u
#308
0&
0-
#309
1&
1-
b10010 y
b11111010000000000000000000000 u
#310
0&
0-
#311
1&
1-
b10011 y
b111110100000000000000000000000 u
#312
0&
0-
#313
1&
1-
b10100 y
b1111101000000000000000000000000 u
#314
0&
0-
#315
1&
1-
b10101 y
b11111010000000000000000000000000 u
#316
0&
0-
#317
1&
1-
b10110 y
b11110100000000000000000000000000 u
b1 v
#318
0&
0-
#319
1&
1-
b10111 y
b11101000000000000000000000000000 u
b11 v
#320
0&
0-
#321
1&
1-
b11000 y
b11010000000000000000000000000000 u
b111 v
#322
0&
0-
#323
1&
1-
b11001 y
b1 v
b10100000000000000000000000000001 u
b11 v
#324
0&
0-
#325
1&
1-
b11010 y
b1000000000000000000000000000010 u
b111 v
#326
0&
0-
#327
1&
1-
b11011 y
b1 v
b10000000000000000000000000000101 u
b10 v
#328
0&
0-
#329
1&
1-
b11100 y
b1010 u
b101 v
#330
0&
0-
#331
1&
1-
b11101 y
b10100 u
b1010 v
#332
0&
0-
#333
1&
1-
b11110 y
b100 v
b101001 u
b1000 v
#334
0&
0-
#335
1&
1-
b11111 y
b10 v
b1010011 u
b100 v
#336
0&
0-
#337
1&
1-
b100000 y
b10100110 u
b1000 v
#338
0&
0-
#339
1&
1-
00
11
b10100110 s
b100 t
b100 %
b10100110 $
1"
0!
#340
0&
0-
#341
1&
1-
01
b0 y
10
b11111010000 u
b0 v
1!
0"
#342
0&
0-
#343
1&
1-
b1 y
b111110100000 u
#344
0&
0-
#345
1&
1-
b10 y
b1111101000000 u
#346
0&
0-
#347
1&
1-
b11 y
b11111010000000 u
#348
0&
0-
#349
1&
1-
b100 y
b111110100000000 u
#350
0&
0-
#351
1&
1-
b101 y
b1111101000000000 u
#352
0&
0-
#353
1&
1-
b110 y
b11111010000000000 u
#354
0&
0-
#355
1&
1-
b111 y
b111110100000000000 u
#356
0&
0-
#357
1&
1-
b1000 y
b1111101000000000000 u
#358
0&
0-
#359
1&
1-
b1001 y
b11111010000000000000 u
#360
0&
0-
#361
1&
1-
b1010 y
b111110100000000000000 u
#362
0&
0-
#363
1&
1-
b1011 y
b1111101000000000000000 u
#364
0&
0-
#365
1&
1-
b1100 y
b11111010000000000000000 u
#366
0&
0-
#367
1&
1-
b1101 y
b111110100000000000000000 u
#368
0&
0-
#369
1&
1-
b1110 y
b1111101000000000000000000 u
#370
0&
0-
#371
1&
1-
b1111 y
b11111010000000000000000000 u
#372
0&
0-
#373
1&
1-
b10000 y
b111110100000000000000000000 u
#374
0&
0-
#375
1&
1-
b10001 y
b1111101000000000000000000000 u
#376
0&
0-
#377
1&
1-
b10010 y
b11111010000000000000000000000 u
#378
0&
0-
#379
1&
1-
b10011 y
b111110100000000000000000000000 u
#380
0&
0-
#381
1&
1-
b10100 y
b1111101000000000000000000000000 u
#382
0&
0-
#383
1&
1-
b10101 y
b11111010000000000000000000000000 u
#384
0&
0-
#385
1&
1-
b10110 y
b11110100000000000000000000000000 u
b1 v
#386
0&
0-
#387
1&
1-
b10111 y
b11101000000000000000000000000000 u
b11 v
#388
0&
0-
#389
1&
1-
b11000 y
b11010000000000000000000000000000 u
b111 v
#390
0&
0-
#391
1&
1-
b11001 y
b1 v
b10100000000000000000000000000001 u
b11 v
#392
0&
0-
#393
1&
1-
b11010 y
b1000000000000000000000000000010 u
b111 v
#394
0&
0-
#395
1&
1-
b11011 y
b1 v
b10000000000000000000000000000101 u
b10 v
#396
0&
0-
#397
1&
1-
b11100 y
b1010 u
b101 v
#398
0&
0-
#399
1&
1-
b11101 y
b10100 u
b1010 v
#400
0&
0-
#401
1&
1-
b11110 y
b100 v
b101001 u
b1000 v
#402
0&
0-
#403
1&
1-
b11111 y
b10 v
b1010011 u
b100 v
#404
0&
0-
#405
1&
1-
b100000 y
b10100110 u
b1000 v
#406
0&
0-
#407
1&
1-
00
11
1"
0!
#408
0&
0-
#409
1&
1-
01
b0 y
10
b11111010000 u
b0 v
1!
0"
#410
0&
0-
#411
1&
1-
b1 y
b111110100000 u
#412
0&
0-
#413
1&
1-
b10 y
b1111101000000 u
#414
0&
0-
#415
b101 ,
1&
1-
b11 y
b11111010000000 u
#416
0&
0-
#417
1&
1-
b100 y
b111110100000000 u
#418
0&
0-
#419
1&
1-
b101 y
b1111101000000000 u
#420
0&
0-
b101 *
1r
0q
#421
1&
1-
b110 y
b11111010000000000 u
#422
0&
0-
#423
1&
1-
b111 y
b111110100000000000 u
#424
0&
0-
#425
1&
1-
b1000 y
b1111101000000000000 u
#426
0&
0-
#427
1&
1-
b1001 y
b11111010000000000000 u
#428
0&
0-
#429
1&
1-
b1010 y
b111110100000000000000 u
#430
0&
0-
#431
1&
1-
b1011 y
b1111101000000000000000 u
#432
0&
0-
#433
1&
1-
b1100 y
b11111010000000000000000 u
#434
0&
0-
#435
1&
1-
b1101 y
b111110100000000000000000 u
#436
0&
0-
#437
1&
1-
b1110 y
b1111101000000000000000000 u
#438
0&
0-
#439
1&
1-
b1111 y
b11111010000000000000000000 u
#440
0&
0-
#441
1&
1-
b10000 y
b111110100000000000000000000 u
#442
0&
0-
#443
1&
1-
b10001 y
b1111101000000000000000000000 u
#444
0&
0-
#445
1&
1-
b10010 y
b11111010000000000000000000000 u
#446
0&
0-
#447
1&
1-
b10011 y
b111110100000000000000000000000 u
#448
0&
0-
#449
1&
1-
b10100 y
b1111101000000000000000000000000 u
#450
0&
0-
#451
1&
1-
b10101 y
b11111010000000000000000000000000 u
#452
0&
0-
#453
1&
1-
b10110 y
b11110100000000000000000000000000 u
b1 v
#454
0&
0-
#455
1&
1-
b10111 y
b11101000000000000000000000000000 u
b11 v
#456
0&
0-
#457
1&
1-
b11000 y
b11010000000000000000000000000000 u
b111 v
#458
0&
0-
#459
1&
1-
b11001 y
b1 v
b10100000000000000000000000000001 u
b11 v
#460
0&
0-
#461
1&
1-
b11010 y
b1000000000000000000000000000010 u
b111 v
#462
0&
0-
#463
1&
1-
b11011 y
b1 v
b10000000000000000000000000000101 u
b10 v
#464
0&
0-
#465
1&
1-
b11100 y
b1010 u
b101 v
#466
0&
0-
#467
1&
1-
b11101 y
b10100 u
b1010 v
#468
0&
0-
#469
1&
1-
b11110 y
b100 v
b101001 u
b1000 v
#470
0&
0-
#471
1&
1-
b11111 y
b10 v
b1010011 u
b100 v
#472
0&
0-
#473
1&
1-
b100000 y
b10100110 u
b1000 v
#474
0&
0-
#475
1&
1-
00
11
1"
0!
#476
0&
0-
#477
1&
1-
01
b0 y
10
b101 x
b11111010000 u
b0 v
1!
0"
#478
0&
0-
#479
1&
1-
b1 y
b111110100000 u
#480
0&
0-
#481
1&
1-
b10 y
b1111101000000 u
#482
0&
0-
#483
1&
1-
b11 y
b11111010000000 u
#484
0&
0-
#485
1&
1-
b100 y
b111110100000000 u
#486
0&
0-
#487
1&
1-
b101 y
b1111101000000000 u
#488
0&
0-
#489
1&
1-
b110 y
b11111010000000000 u
#490
0&
0-
#491
1&
1-
b111 y
b111110100000000000 u
#492
0&
0-
#493
1&
1-
b1000 y
b1111101000000000000 u
#494
0&
0-
#495
1&
1-
b1001 y
b11111010000000000000 u
#496
0&
0-
#497
1&
1-
b1010 y
b111110100000000000000 u
#498
0&
0-
#499
1&
1-
b1011 y
b1111101000000000000000 u
#500
0&
0-
#501
1&
1-
b1100 y
b11111010000000000000000 u
#502
0&
0-
#503
1&
1-
b1101 y
b111110100000000000000000 u
#504
0&
0-
#505
1&
1-
b1110 y
b1111101000000000000000000 u
#506
0&
0-
#507
1&
1-
b1111 y
b11111010000000000000000000 u
#508
0&
0-
#509
1&
1-
b10000 y
b111110100000000000000000000 u
#510
0&
0-
#511
1&
1-
b10001 y
b1111101000000000000000000000 u
#512
0&
0-
#513
1&
1-
b10010 y
b11111010000000000000000000000 u
#514
0&
0-
#515
1&
1-
b10011 y
b111110100000000000000000000000 u
#516
0&
0-
#517
1&
1-
b10100 y
b1111101000000000000000000000000 u
#518
0&
0-
#519
1&
1-
b10101 y
b11111010000000000000000000000000 u
#520
0&
0-
#521
1&
1-
b10110 y
b11110100000000000000000000000000 u
b1 v
#522
0&
0-
#523
1&
1-
b10111 y
b11101000000000000000000000000000 u
b11 v
#524
0&
0-
#525
1&
1-
b11000 y
b11010000000000000000000000000000 u
b111 v
#526
0&
0-
#527
1&
1-
b11001 y
b10 v
b10100000000000000000000000000001 u
b101 v
#528
0&
0-
#529
1&
1-
b11010 y
b0 v
b1000000000000000000000000000011 u
b1 v
#530
0&
0-
#531
1&
1-
b11011 y
b10000000000000000000000000000110 u
b10 v
#532
0&
0-
#533
1&
1-
b11100 y
b1100 u
b101 v
#534
0&
0-
#535
1&
1-
b11101 y
b0 v
b11001 u
#536
0&
0-
#537
1&
1-
b11110 y
b110010 u
#538
0&
0-
#539
1&
1-
b11111 y
b1100100 u
#540
0&
0-
#541
1&
1-
b100000 y
b11001000 u
#542
0&
0-
#543
1&
1-
00
11
b11001000 s
b0 t
b0 %
b11001000 $
1"
0!
#544
0&
0-
#545
1&
1-
01
b0 y
10
b11111010000 u
1!
0"
#546
0&
0-
#547
1&
1-
b1 y
b111110100000 u
#548
0&
0-
#549
1&
1-
b10 y
b1111101000000 u
#550
0&
0-
#551
1&
1-
b11 y
b11111010000000 u
#552
0&
0-
#553
1&
1-
b100 y
b111110100000000 u
#554
0&
0-
#555
1&
1-
b101 y
b1111101000000000 u
#556
0&
0-
#557
1&
1-
b110 y
b11111010000000000 u
#558
0&
0-
#559
1&
1-
b111 y
b111110100000000000 u
#560
0&
0-
#561
1&
1-
b1000 y
b1111101000000000000 u
#562
0&
0-
#563
1&
1-
b1001 y
b11111010000000000000 u
#564
0&
0-
#565
1&
1-
b1010 y
b111110100000000000000 u
#566
0&
0-
#567
1&
1-
b1011 y
b1111101000000000000000 u
#568
0&
0-
#569
1&
1-
b1100 y
b11111010000000000000000 u
#570
0&
0-
#571
1&
1-
b1101 y
b111110100000000000000000 u
#572
0&
0-
#573
1&
1-
b1110 y
b1111101000000000000000000 u
#574
0&
0-
#575
1&
1-
b1111 y
b11111010000000000000000000 u
#576
0&
0-
#577
1&
1-
b10000 y
b111110100000000000000000000 u
#578
0&
0-
#579
1&
1-
b10001 y
b1111101000000000000000000000 u
#580
0&
0-
#581
1&
1-
b10010 y
b11111010000000000000000000000 u
#582
0&
0-
#583
1&
1-
b10011 y
b111110100000000000000000000000 u
#584
0&
0-
